setvis/__init__.py
setvis/history.py
setvis/membership.py
setvis/plots.py
setvis/plotutils.py
setvis/setexpression.py
setvis-0.1rc5.dist-info/LICENCE
setvis-0.1rc5.dist-info/METADATA
setvis-0.1rc5.dist-info/WHEEL
setvis-0.1rc5.dist-info/RECORD
