Metadata-Version: 2.1
Name: setvis
Version: 0.1rc5
Summary: Visualize set membership and missing data
Home-page: https://github.com/alan-turing-institute/setvis
License: Apache-2.0
Author: The Setvis Maintainers
Requires-Python: >=3.9
Classifier: Framework :: Jupyter
Classifier: Intended Audience :: Science/Research
Classifier: License :: OSI Approved :: Apache Software License
Classifier: Programming Language :: Python :: 3
Classifier: Programming Language :: Python :: 3.9
Classifier: Programming Language :: Python :: 3.10
Classifier: Programming Language :: Python :: 3.11
Classifier: Programming Language :: Python :: 3.12
Classifier: Programming Language :: Python :: 3.13
Classifier: Topic :: Scientific/Engineering :: Information Analysis
Classifier: Topic :: Scientific/Engineering :: Visualization
Provides-Extra: all
Provides-Extra: db
Provides-Extra: doc
Provides-Extra: extra
Provides-Extra: notebooks
Provides-Extra: performance-extras
Provides-Extra: test
Requires-Dist: Bottleneck (>=1.3,<2.0) ; extra == "performance-extras" or extra == "all"
Requires-Dist: Sphinx (>=4.3) ; extra == "doc" or extra == "extra" or extra == "all"
Requires-Dist: bokeh (>=3.4,<4.0)
Requires-Dist: matplotlib (>=3.4,<4.0) ; extra == "notebooks" or extra == "extra" or extra == "all"
Requires-Dist: notebook (>=6.4,<8) ; extra == "notebooks" or extra == "extra" or extra == "all"
Requires-Dist: numexpr (>=2.7,<3.0) ; extra == "performance-extras" or extra == "all"
Requires-Dist: numpy (>=1.21,<3)
Requires-Dist: pandas (>=1.3,<3)
Requires-Dist: psycopg2-binary (>=2.9,<3.0) ; extra == "db" or extra == "all"
Requires-Dist: pydantic (>=1.8,<3)
Requires-Dist: pydata-sphinx-theme (>=0.7,<0.8) ; extra == "doc" or extra == "extra" or extra == "all"
Requires-Dist: pytest (>=6.2) ; extra == "test" or extra == "extra" or extra == "all"
Requires-Dist: scikit-learn (>=0.2,<2) ; extra == "notebooks" or extra == "extra" or extra == "all"
Requires-Dist: scipy (>=1.7,<2.0)
Requires-Dist: setuptools (>=68.1)
Requires-Dist: tomli (>=2.0,<3.0)
Project-URL: Documentation, https://setvis.readthedocs.io/en/latest/
Project-URL: Repository, https://github.com/alan-turing-institute/setvis
